[
        {
            "que": "北斗七星高，哥舒夜带刀。",
            "answer": "哥舒：指哥舒翰，是唐玄宗的大将，突厥族哥舒部的后裔。哥舒是以部落名称作为姓氏。《全唐诗》题下注：“天宝中，哥舒翰为安西节度使，控地数千里，甚著威令，故西鄙人歌此。”"
        },
        {
            "que": "欲得周郎顾，时时误拂弦。",
            "answer": "周郎：指三国时吴将周瑜。他二十四岁为大将，时人称其为“周郎”。他精通音乐，听人奏错曲时，即使喝得半醉，也会转过头看一下奏者。当时人称：“曲有误，周郎顾。”"
        },
        {
            "que": "一声何满子，双泪落君前。",
            "answer": "何满子：唐教坊曲名。《乐府诗集》载白居易语：“何满子，开元中沧州歌者，临刑进此曲以赎死，竞不得免。”《何满子》曲调悲绝，白居易《何满子》诗中说它“一曲四词歌八叠，从头便是断肠声。”"
        },
        {
            "que": "莫买沃洲山，时人已知处。",
            "answer": "沃洲山：在浙江省新昌县东，相传为晋代高僧支遁放鹤养马处，有放鹤峰，养马坡，道家列为第十二洞天福地。"
        },
        {
            "que": "昨夜风开露井桃，未央前殿月轮高。",
            "answer": "未央：即未央宫​，汉宫殿名，汉高祖刘邦​所建。也指唐宫。"
        },
        {
            "que": "遥知兄弟登高处，遍插茱萸少一人。",
            "answer": "茱萸（zhūyú）：是指吴茱萸。为芸香科植物吴茱萸的近成熟果实。《本草纲目》吴茱萸【集解】苏颂引周处《风土记》云：“俗尚九月九日谓之上九，茱萸到此日气烈熟色赤，可折其房以插头，云辟恶气御冬。”又《续齐谐记》云：“汝南桓景随费长房学道，长房谓曰：‘九月九日，汝家有灾厄，宜令急去，各作绛囊盛茱萸以系臂上，登高饮菊花酒，此祸可消。’景如其言，举家登高山，夕还，见鸡犬牛羊一时暴死。长房闻之曰：‘此代之矣。’故人至此日，登高饮酒，戴茱萸囊，由此尔。”由此可见，王维诗中的茱萸，当是指吴茱萸。"
        },
        {
            "que": "朝辞白帝彩云间，千里江陵一日还。",
            "answer": "白帝城：故址在今重庆市奉节县白帝山上。杨齐贤注：“白帝城，公孙述所筑。初，公孙述至鱼复，有白龙出井中，自以承汉土运，故称白帝，改鱼复为白帝城。”王琦注：“白帝城，在夔州奉节县，与巫山相近。所谓彩云，正指巫山之云也。”"
        },
        {
            "que": "回乐烽前沙似雪，受降城外月如霜。",
            "answer": "受降城：唐初名将张仁愿​为了防御突厥，在黄河以北筑受降城，分东、中、西三城，都在今内蒙古自治区境内。另有一种说法是：公元646年（贞观二十年），唐太宗亲临灵州接受突厥一部的投降，“受降城”之名即由此而来。"
        },
        {
            "que": "乘兴南游不戒严，九重谁省谏书函。",
            "answer": "乘兴句：《晋书·舆服志》：“凡车驾亲戎，中外戒严。”此言不戒严，意谓炀帝骄横无忌，毫无戒备。"
        },
        {
            "que": "瑶池阿母绮窗开，黄竹歌声动地哀。",
            "answer": "瑶池阿母：《穆天子传》卷三：“天子宾于西王母，天子觞西王母于瑶池之上。西王母为天子谣曰：‘白云在天，山陵自出。道里悠远，山川间之。将子无死，尚能复来。’天子答之曰：‘予归东土，和治诸夏。万民平均，吾顾见汝。比及三年，将复而野。’”《武帝内传》称王母为“玄都阿母”。；黄竹歌声：《穆天子传》卷五：“日中大寒，北风雨雪，有冻人。天子作诗三章以哀民。”"
        },
        {
            "que": "八骏日行三万里，穆王何事不重来。",
            "answer": "穆王：西周人，姓姬名满，传说他曾周游天下。；八骏：传说周穆王有八匹骏马，可日行三万里。《列子》、《穆天子传》等记载不一。"
        },
        {
            "que": "何当共剪西窗烛，却话巴山夜雨时。",
            "answer": "剪西窗烛：剪烛，剪去燃焦的烛芯，使灯光明亮。这里形容深夜秉烛长谈。“西窗话雨”“西窗剪烛”用作成语，所指也不限于夫妇，有时也用以写朋友间的思念之情。"
        },
        {
            "que": "休问梁园旧宾客，茂陵秋雨病相如。",
            "answer": "梁园：梁孝王在梁地大兴土木，以睢阳为中心，根据自然景色，修建了一个很大的花园，称东苑，也叫菟园，后人称为梁园。"
        },
        {
            "que": "无端嫁得金龟婿，辜负香衾事早朝。",
            "answer": "金龟婿：佩带金龟（即作官）的丈夫。《新唐书·车服志》：“天授二年，改佩鱼皆为龟，其后三品以上龟袋饰以金。”"
        },
        {
            "que": "岐王宅里寻常见，崔九堂前几度闻。",
            "answer": "岐王：唐玄宗李隆基的弟弟李隆范（后改名李范），以好学爱才著称，雅善音律。；崔九：崔涤，在兄弟中排行第九，中书令崔湜的弟弟。玄宗时，曾任殿中监，出入禁中，得玄宗宠幸。崔姓，是当时一家大姓，以此表明李龟年原来受赏识。"
        },
        {
            "que": "日暮东风怨啼鸟，落花犹似坠楼人。",
            "answer": "坠楼人：指石崇爱妾绿珠，为石崇坠楼而死。"
        },
        {
            "que": "繁华事散逐香尘，流水无情草自春。",
            "answer": "香尘：石崇为教练家中舞妓步法，以沉香屑铺象牙床上，使她们践踏，无迹者赐以珍珠。"
        },
        {
            "que": "二十四桥明月夜，玉人何处教吹箫？",
            "answer": "二十四桥：一说为二十四座桥。北宋沈括《梦溪笔谈·补笔谈》卷三中对每座桥的方位和名称一一做了记载。一说有一座桥名叫二十四桥，清李斗《扬州画舫录》卷十五：“廿四桥即吴家砖桥，一名红药桥，在熙春台后，……扬州鼓吹词序云，是桥因古二十四美人吹箫于此，故名。”"
        },
        {
            "que": "落魄江湖载酒行，楚腰纤细掌中轻。",
            "answer": "掌中轻：汉成帝皇后赵飞燕“体轻，能为掌上舞”（《飞燕外传》）。"
        },
        {
            "que": "东风不与周郎便，铜雀春深锁二乔。",
            "answer": "周郎：指周瑜，字公瑾，年轻时即有才名，人呼周郎。后任吴军大都督，曾参与赤壁之战并为此战役中的主要人物。；二乔：东吴乔公的两个女儿，一嫁前国主孙策（孙权兄），称大乔，一嫁军事统帅周瑜，称小乔，合称“二乔”。；铜雀：即铜雀台，曹操在今河北省临漳县建造的一座楼台，楼顶里有大铜雀，台上住姬妾歌妓，是曹操暮年行乐处。"
        }
]